README.md
setup.py
extra_magics/__init__.py
extra_magics/bq_estimation.py
extra_magics/cell_execution.py
extra_magics/notifier.py
extra_magics/super_run.py
jupyter_extra_magics.egg-info/PKG-INFO
jupyter_extra_magics.egg-info/SOURCES.txt
jupyter_extra_magics.egg-info/dependency_links.txt
jupyter_extra_magics.egg-info/requires.txt
jupyter_extra_magics.egg-info/top_level.txt