Metadata-Version: 2.1
Name: jupyter-extra-magics
Version: 1.0.4
Summary: A Jupyter magics and tools to extend Jupyter env
Home-page: UNKNOWN
License: MIT
Platform: UNKNOWN
Classifier: License :: OSI Approved :: MIT License
Classifier: Programming Language :: Python :: 3
Classifier: Programming Language :: Python :: 3.7
